LICENSE
MANIFEST.in
README.md
package.json
setup.py
dash_kaplan_meier/DashKaplanMeier.py
dash_kaplan_meier/__init__.py
dash_kaplan_meier/_imports_.py
dash_kaplan_meier/async-DashKaplanMeier.js
dash_kaplan_meier/async-DashKaplanMeier.js.map
dash_kaplan_meier/dash_kaplan_meier.min.js
dash_kaplan_meier/dash_kaplan_meier.min.js.map
dash_kaplan_meier/metadata.json
dash_kaplan_meier/package-info.json
dash_kaplan_meier/survival_stats.py
dash_kaplan_meier.egg-info/PKG-INFO
dash_kaplan_meier.egg-info/SOURCES.txt
dash_kaplan_meier.egg-info/dependency_links.txt
dash_kaplan_meier.egg-info/requires.txt
dash_kaplan_meier.egg-info/top_level.txt