Metadata-Version: 2.1
Name: dash-kaplan-meier
Version: 0.0.6
Summary: Reusable React-based UI for Dash apps that computes and plots a Kaplan-Meier curve entirely using raw event and time-to-event data passed from Dash app. It eliminates analysis libraries, making it lightweight and frontend-driven.
Home-page: https://github.com/XLlobet/dash-kaplan-meier
Author: Xavier Llobet
Author-email: llbt.nvs.x@gmail.com
License: MIT
Platform: UNKNOWN
Classifier: Framework :: Dash
License-File: LICENSE
